resilient_app_config_plugins/__init__.py
resilient_app_config_plugins/constants.py
resilient_app_config_plugins/cyberark.py
resilient_app_config_plugins/hashicorp.py
resilient_app_config_plugins/keyring.py
resilient_app_config_plugins/plugin_base.py
resilient_app_config_plugins-1.0.3.dist-info/METADATA
resilient_app_config_plugins-1.0.3.dist-info/WHEEL
resilient_app_config_plugins-1.0.3.dist-info/top_level.txt
resilient_app_config_plugins-1.0.3.dist-info/RECORD
