Metadata-Version: 2.4
Name: resilient_app_config_plugins
Version: 1.0.3
Summary: Python base package for IBM SOAR apps App Config Plugins
Home-page: https://github.com/ibmresilient/resilient-python-api/tree/main/resilient-app-config-plugins
Author: IBM SOAR
License: MIT
Project-URL: Documentation, https://ibm.biz/soar-docs
Project-URL: API Docs, https://ibm.biz/soar-python-docs
Project-URL: IBM Community, https://ibm.biz/soarcommunity
Keywords: ibm,soar,resilient,resilient-circuits,circuits,resilient-sdk,sdk,plugins,resilient-plugins,app-config-plugins
Classifier: Programming Language :: Python :: 2.7
Classifier: Programming Language :: Python :: 3.6
Classifier: Programming Language :: Python :: 3.9
Classifier: Programming Language :: Python :: 3.11
Classifier: Programming Language :: Python :: 3.12
Requires-Python: !=3.0.*,!=3.1.*,!=3.2.*,!=3.3.*,!=3.4.*,!=3.5.*,>=2.7
Requires-Dist: requests~=2.27
Requires-Dist: six~=1.16
Requires-Dist: requests-pkcs12==1.27; python_version >= "3.6"
Requires-Dist: requests-pkcs12==1.10; python_version == "2.7"
Requires-Dist: keyring~=23.5; python_version > "3.6"
Requires-Dist: keyring~=23.4; python_version == "3.6"
Requires-Dist: keyring==18.0.1; python_version == "2.7"
Requires-Dist: cachetools~=5.0; python_version > "3.6"
Requires-Dist: cachetools~=2.1; python_version <= "3.6"
